{
    "os": "Linux-5.4.0-73-generic-x86_64-with-debian-buster-sid",
    "python": "3.7.10",
    "heartbeatAt": "2021-06-10T13:37:12.650823",
    "startedAt": "2021-06-10T13:37:10.691307",
    "docker": null,
    "gpu": "GeForce RTX 2080 Ti",
    "gpu_count": 2,
    "cpu_count": 48,
    "cuda": "10.1.243",
    "args": [],
    "state": "running",
    "program": "main_wandb.py",
    "codePath": "main_wandb.py",
    "git": {
        "remote": "https://github.com/xiaomingaaa/kg-mtl.git",
        "commit": "8880dc0fcfb73b5276bd7a1a8b4f5df9b105c2f0"
    },
    "email": "13693963350@163.com",
    "root": "/home/mtf/mtf/kg-mtl",
    "host": "ubuntu-SYS-7048GR-TR",
    "username": "mtf",
    "executable": "/home/mtf/.conda/envs/kg-mtl/bin/python"
}
